packaging_repositories/__init__.py
packaging_repositories/entries.py
packaging_repositories/fetchers.py
packaging_repositories/filters.py
packaging_repositories/repositories.py
packaging_repositories/utils.py
packaging_repositories-0.2.0.dist-info/METADATA
packaging_repositories-0.2.0.dist-info/RECORD
packaging_repositories-0.2.0.dist-info/WHEEL
packaging_repositories-0.2.0.dist-info/top_level.txt
packaging_repositories-0.2.0.dist-info/zip-safe
