Metadata-Version: 2.1
Name: packaging-repositories
Version: 0.2.0
Summary: pip package finder extraction prototype.
Home-page: https://github.com/uranusjr/packaging-repositories
Author: Tzu-ping Chung
Author-email: uranusjr@gmail.com
License: ISC License
Platform: UNKNOWN
Classifier: Development Status :: 1 - Planning
Classifier: License :: OSI Approved :: ISC License (ISCL)
Classifier: Operating System :: OS Independent
Classifier: Programming Language :: Python :: 2
Classifier: Programming Language :: Python :: 2.6
Classifier: Programming Language :: Python :: 2.7
Classifier: Programming Language :: Python :: 3
Classifier: Programming Language :: Python :: 3.4
Classifier: Programming Language :: Python :: 3.5
Classifier: Programming Language :: Python :: 3.6
Classifier: Programming Language :: Python :: 3.7
Classifier: Topic :: Software Development :: Libraries :: Python Modules
Requires-Python: >=2.6,!=3.0,!=3.1,!=3.2,!=3.3
Provides-Extra: tests
Requires-Dist: packaging
Provides-Extra: tests
Requires-Dist: pytest; extra == 'tests'
Requires-Dist: requests; extra == 'tests'
Provides-Extra: tests
Requires-Dist: aiohttp; (python_version >= "3.6") and extra == 'tests'
